{
  "tree": {
    "id": "root",
    "title": "Vector Projection",
    "summary": "This tutorial explains vector projection, covering its definition, mathematical formula, unit vector representation, practical applications, and provides interactive experiments to help visualize how one vector projects onto another.",
    "children": [
      {
        "id": "section-0",
        "title": "1. Interactive Playground",
        "summary": "This section describes an interactive tool where users can manipulate vector endpoints by dragging or editing values to visualize the projection of vector a onto vector b, which is displayed in green.",
        "contentHash": "ce8140b074d1",
        "children": [
          {
            "id": "section-0-chunk-0",
            "title": "Interactive Vector Projection Playground",
            "summary": "An interactive tool where users can manipulate vector endpoints and see the projection of vector a onto vector b displayed in green.",
            "sourceText": "1. Interactive Playground] Drag the endpoints of the vectors, or edit the values directly below. The  green vector  shows the projection of  a  onto  b .",
            "sourceAnchor": {
              "startChar": 0,
              "endChar": 153,
              "startMarker": "1. Interactive Playground] Drag the endpoints of the vectors",
              "endMarker": "shows the projection of  a  onto  b ."
            },
            "sectionIndex": 0,
            "isLeaf": true,
            "canExpand": true,
            "expanded": false
          }
        ]
      },
      {
        "id": "section-1",
        "title": "2. What is Vector Projection?",
        "summary": "Vector projection finds the \"shadow\" or component of one vector that lies along the direction of another vector, essentially determining how much of the first vector points in the same direction as the second.",
        "contentHash": "eb179dae7845",
        "children": [
          {
            "id": "section-1-chunk-0",
            "title": "Vector Projection Definition and Streetlight Analogy",
            "summary": "Vector projection is explained through a streetlight shadow analogy, showing how one vector creates a 'shadow' onto another vector.",
            "sourceText": "Imagine you're standing under a streetlight, and your shadow falls on the ground. The shadow is a projection of you onto the ground plane. Vector projection works the same way: we're finding the \"shadow\" of one vector onto another.",
            "sourceAnchor": {
              "startChar": 31,
              "endChar": 262,
              "startMarker": "Imagine you're standing under a streetlight, and your shadow falls on the ground.",
              "endMarker": "we're finding the \"shadow\" of one vector onto another."
            },
            "sectionIndex": 1,
            "isLeaf": true,
            "canExpand": true,
            "expanded": false
          },
          {
            "id": "section-1-chunk-1",
            "title": "Mathematical Purpose of Vector Projection",
            "summary": "Vector projection finds the component of one vector that lies along the direction of another vector.",
            "sourceText": "Specifically, we want to find the component of vector  a  that lies along the direction of vector  b . \nThe projection answers: \"How much of a points in the same direction as b?\"",
            "sourceAnchor": {
              "startChar": 263,
              "endChar": 441,
              "startMarker": "Specifically, we want to find the component of vector  a  that lies along the direction of vector  b .",
              "endMarker": "How much of a points in the same direction as b?\""
            },
            "sectionIndex": 1,
            "isLeaf": true,
            "canExpand": true,
            "expanded": false
          }
        ]
      },
      {
        "id": "section-2",
        "title": "3. The Formula",
        "summary": "The projection of vector a onto vector b is calculated using the formula proj_b(a) = ((a · b) / |b|²) × b, which measures how much of vector a points in the same direction as vector b.",
        "contentHash": "4b0234e21c76",
        "children": [
          {
            "id": "section-2-chunk-0",
            "title": "Vector Projection Formula Introduction",
            "summary": "The basic formula for projecting vector a onto vector b is presented with its mathematical notation.",
            "sourceText": "The projection of vector  a  onto vector  b  is: \nproj_b(a) = ((a · b) / |b|²) × b Let's break this down:",
            "sourceAnchor": {
              "startChar": 16,
              "endChar": 121,
              "startMarker": "The projection of vector  a  onto vector  b  is:",
              "endMarker": "Let's break this down:"
            },
            "sectionIndex": 2,
            "isLeaf": true,
            "canExpand": true,
            "expanded": false
          },
          {
            "id": "section-2-chunk-1",
            "title": "When Vectors Are Equal: Pythagorean Connection",
            "summary": "Explores what happens when vector A equals vector B and how this relates to the Pythagorean theorem through dot products.",
            "sourceText": "Hey, if vector A were the same as vector B, wouldn't this just be the Pythagorean formula? a*a + b*b = c * c?] \n[CALLOUT: About \"a₁×b₁ + a₂×b₂\" You're absolutely right to notice that connection! When vector A equals vector B, the dot product A·A does become a₁² + a₂², which is indeed related to the Pythagorean theorem. This gives us the square of the vector's length (or magnitude). \nHowever, there's a subtle but important difference from the traditional Pythagorean formula c² = a² + b². In the vector case, a₁ and a₂ are the components of a single vector - they're like the horizontal and vertical \"legs\" of that vector. So a₁² + a₂² equals the square of the vector's length, not the length itself. \nThis is actually a key insight: the dot product of a vector with itself tells us how \"long\" that vector is (squared). But when we take the dot product of two different vectors, we're measuring something else entirely - how much they point in the same direction. The formula stays the same, but the geometric meaning changes completely depending on whether we're using the same vector twice or two different vectors.",
            "sourceAnchor": {
              "startChar": 140,
              "endChar": 1260,
              "startMarker": "Hey, if vector A were the same as vector B, wouldn't this just be the Pythagorean formula?",
              "endMarker": "The formula stays the same, but the geometric meaning changes completely depending on whether we're using the same vector twice or two different vectors."
            },
            "sectionIndex": 2,
            "isLeaf": true,
            "canExpand": true,
            "expanded": false
          },
          {
            "id": "section-2-chunk-2",
            "title": "Two Different Vectors and Right Triangles",
            "summary": "Demonstrates how dot products work with two different vectors using right triangles and explains the geometric relationship between vector projections.",
            "sourceText": "If the vector is the hypotenuse, and the x and y components are the other sides, then show how this math works with two different vectors (ideally a diagram of two right triangles and the math of the dot product)] \n[CALLOUT: About \"how much they point in the same direction\" Picture two vectors: vector A pointing at (3,4) and vector B pointing at (6,2). Each forms its own right triangle with the axes - A has legs of 3 and 4, while B has legs of 6 and 2. \nWhen we compute their dot product A·B = (3)(6) + (4)(2) = 18 + 8 = 26, we're not just multiplying corresponding components randomly. We're actually measuring how much of vector A's \"effort\" goes in the same direction as vector B. Think of it this way: if you project A onto B's direction, the dot product tells you the length of that projection multiplied by B's length. \nThe key insight is that while each vector individually uses the Pythagorean theorem (A's length is √(3²+4²) = 5, B's length is √(6²+2²) = √40), the dot product captures something different entirely. It's measuring the geometric relationship between the two triangles - specifically, how aligned their hypotenuses are. If the vectors pointed in exactly the same direction, the dot product would equal the product of their lengths. If they were perpendicular, it would be zero, regardless of how long each hypotenuse is.",
            "sourceAnchor": {
              "startChar": 1302,
              "endChar": 2650,
              "startMarker": "If the vector is the hypotenuse, and the x and y components are the other sides, then show how this math works with two different vectors",
              "endMarker": "If they were perpendicular, it would be zero, regardless of how long each hypotenuse is."
            },
            "sectionIndex": 2,
            "isLeaf": true,
            "canExpand": true,
            "expanded": false
          },
          {
            "id": "section-2-chunk-3",
            "title": "Why Multiplication Instead of Addition",
            "summary": "Explains why dot products use multiplication to capture directional agreement between vectors rather than addition which would miss alignment information.",
            "sourceText": "Why do we use multiplication here instead of addition?] \n[CALLOUT: About \"dot product\" Multiplication captures how much two vectors \"agree\" in each direction, while addition would just combine their magnitudes without considering alignment. \nThink of it this way: if both vectors point strongly in the same direction (both components are positive and large), multiplying gives you a big positive number, showing strong agreement. If they point in opposite directions (one positive, one negative), multiplication gives you a negative number, showing disagreement. Addition would miss this directional relationship entirely. \nFor example, if vector a = (3, 4) and vector b = (2, 1), the dot product is 3×2 + 4×1 = 10. Both vectors have positive components, so they generally point in the same direction. But if b = (-2, -1), you get 3×(-2) + 4×(-1) = -10, showing they point in opposite directions. If we used addition instead (3+2 + 4+1 = 10 vs 3+(-2) + 4+(-1) = 4), we'd lose this crucial directional information that tells us whether the vectors align or oppose each other. \nThis directional agreement is exactly what we need for vector projection - we need to know how much one vector extends in the direction of another.",
            "sourceAnchor": {
              "startChar": 2692,
              "endChar": 3915,
              "startMarker": "Why do we use multiplication here instead of addition?",
              "endMarker": "we need to know how much one vector extends in the direction of another."
            },
            "sectionIndex": 2,
            "isLeaf": true,
            "canExpand": true,
            "expanded": false
          },
          {
            "id": "section-2-chunk-4",
            "title": "Fourier Transform Connection and Resonance Pattern",
            "summary": "Draws parallels between dot products and Fourier transforms, showing how both measure agreement or resonance between mathematical objects.",
            "sourceText": "Hey, this is like (naive) Fourier transforms! You look at each point of a signal and multiply it against the sin value of a particular frequency, and if there's a wave at that frequency in your signal, sin(wave) * signal(thatpoint) will always be positive! Great observation! You've hit on a fundamental pattern that appears throughout mathematics and signal processing. In Fourier transforms, you're essentially measuring how much your signal \"agrees\" with a specific frequency by multiplying them pointwise - when they're in phase (both positive or both negative), you get positive contributions that accumulate, and when they're out of phase, you get cancellation. \nThis same principle is exactly what's happening in vector dot products. When we multiply corresponding components of two vectors, we're checking their agreement in each dimensional direction. If both vectors point in the same direction along an axis, we get positive contribution. If they point in opposite directions, we get negative contribution (disagreement). The final dot product sums up all these directional agreements, giving us a single number that captures the overall alignment between the vectors. \nThis is why the dot product is so central to vector projection - it's literally measuring how much one vector \"resonates\" with another, just like your Fourier example measures how much a signal resonates with a particular frequency. That's also why we can use the dot product to find the component of one vector that lies along another vector's direction, which is the essence of projection.",
            "sourceAnchor": {
              "startChar": 3966,
              "endChar": 5538,
              "startMarker": "Hey, this is like (naive) Fourier transforms! You look at each point of a signal",
              "endMarker": "which is the essence of projection."
            },
            "sectionIndex": 2,
            "isLeaf": true,
            "canExpand": true,
            "expanded": false
          },
          {
            "id": "section-2-chunk-5",
            "title": "Converting to Scalar Value",
            "summary": "Explains how the dot product division creates a scalar that measures how much of one vector lies in another's direction.",
            "sourceText": "When we divide the dot product by the squared length of vector b, we're converting a vector operation into a simple number. This scalar is crucial because it gives us the exact measurement of how much of vector a lies in the direction of vector b, expressed as a multiple of b's length.",
            "sourceAnchor": {
              "startChar": 5608,
              "endChar": 5894,
              "startMarker": "When we divide the dot product by the squared length of vector b, we're converting a vector operation into a simple number.",
              "endMarker": "expressed as a multiple of b's length."
            },
            "sectionIndex": 2,
            "isLeaf": true,
            "canExpand": true,
            "expanded": false
          }
        ]
      },
      {
        "id": "section-3",
        "title": "4. Alternative Form: Unit Vectors",
        "summary": "When vector b is normalized to a unit vector b̂, the projection formula simplifies to proj_b(a) = (a · b̂) × b̂, where the dot product directly gives the scalar projection length.",
        "contentHash": "0aa84cb51617",
        "children": [
          {
            "id": "section-3-chunk-0",
            "title": "Normalizing Vector b to Unit Vector",
            "summary": "The first step involves converting vector b into a unit vector b̂ with length 1.",
            "sourceText": "If we first normalize  b  to a unit vector  b̂  (length = 1), the formula simplifies:",
            "sourceAnchor": {
              "startChar": 35,
              "endChar": 120,
              "startMarker": "If we first normalize  b  to a unit vector",
              "endMarker": "the formula simplifies:"
            },
            "sectionIndex": 3,
            "isLeaf": true,
            "canExpand": true,
            "expanded": false
          },
          {
            "id": "section-3-chunk-1",
            "title": "Simplified Projection Formula with Unit Vectors",
            "summary": "When using unit vectors, the projection formula becomes proj_b(a) = (a · b̂) × b̂.",
            "sourceText": "proj_b(a) = (a · b̂) × b̂ Here, (a · b̂) directly gives us the scalar projection — the signed length of the projection.",
            "sourceAnchor": {
              "startChar": 122,
              "endChar": 241,
              "startMarker": "proj_b(a) = (a · b̂) × b̂",
              "endMarker": "the signed length of the projection."
            },
            "sectionIndex": 3,
            "isLeaf": true,
            "canExpand": true,
            "expanded": false
          },
          {
            "id": "section-3-chunk-2",
            "title": "Converting Scalar to Vector Projection",
            "summary": "Multiplying the scalar projection by the unit vector b̂ converts it back to a vector form.",
            "sourceText": "Multiplying by b̂ converts it back to a vector.",
            "sourceAnchor": {
              "startChar": 242,
              "endChar": 289,
              "startMarker": "Multiplying by b̂ converts it back to a vector.",
              "endMarker": "Multiplying by b̂ converts it back to a vector."
            },
            "sectionIndex": 3,
            "isLeaf": true,
            "canExpand": true,
            "expanded": false
          }
        ]
      },
      {
        "id": "section-4",
        "title": "5. Why Does This Matter?",
        "summary": "Vector projection is widely used across various technical fields due to its fundamental importance in mathematical applications.",
        "contentHash": "217ee30a5e4c",
        "children": [
          {
            "id": "section-4-chunk-0",
            "title": "Importance of Vector Projection in Technical Fields",
            "summary": "Vector projection is a fundamental concept that appears extensively across various technical disciplines.",
            "sourceText": "Vector projection appears everywhere in technical fields:",
            "sourceAnchor": {
              "startChar": 26,
              "endChar": 83,
              "startMarker": "Vector projection appears everywhere in technical fields:",
              "endMarker": "Vector projection appears everywhere in technical fields:"
            },
            "sectionIndex": 4,
            "isLeaf": true,
            "canExpand": true,
            "expanded": false
          }
        ]
      },
      {
        "id": "section-5",
        "title": "6. Experiments to Try",
        "summary": "This section encourages readers to return to a previous visualization and conduct experiments, with a hint that projection magnitude depends only on the angle between vectors, not the length of vector b.",
        "contentHash": "d8c22c8b5f3e",
        "children": [
          {
            "id": "section-5-chunk-0",
            "title": "Experiments Introduction and Setup",
            "summary": "Introduction to hands-on experiments using the visualization above to explore vector projection concepts.",
            "sourceText": "Go back to the visualization above and try these experiments:",
            "sourceAnchor": {
              "startChar": 23,
              "endChar": 84,
              "startMarker": "Go back to the visualization above and try these experiments:",
              "endMarker": "Go back to the visualization above and try these experiments:"
            },
            "sectionIndex": 5,
            "isLeaf": true,
            "canExpand": true,
            "expanded": false
          },
          {
            "id": "section-5-chunk-1",
            "title": "Key Insight About Projection Magnitude",
            "summary": "The projection's magnitude depends only on the angle between vectors, not on the length of vector b.",
            "sourceText": "Hint: The projection's magnitude only depends on the angle between the vectors, not on the length of b!",
            "sourceAnchor": {
              "startChar": 97,
              "endChar": 200,
              "startMarker": "Hint: The projection's magnitude only depends on the angle between the vectors, not on the length of b!",
              "endMarker": "Hint: The projection's magnitude only depends on the angle between the vectors, not on the length of b!"
            },
            "sectionIndex": 5,
            "isLeaf": true,
            "canExpand": true,
            "expanded": false
          }
        ]
      },
      {
        "id": "section-6",
        "title": "Section 7",
        "summary": "The scalar in vector projection, calculated as (a·b)/|b|², determines how far along vector b the projection extends, serving as a coordinate that specifies the exact location of the projected point on b's direction.",
        "contentHash": "5b216ad7e8e9",
        "children": [
          {
            "id": "section-6-chunk-0",
            "title": "The Scalar as Heart of Vector Projection",
            "summary": "The scalar from vector projection tells us exactly how far along vector b the projection extends, providing the crucial coordinate information.",
            "sourceText": "This scalar is the heart of vector projection - it's the coordinate that tells us exactly where the projection lands on vector b. Without it, we'd just know the direction (which is b's direction), but not how far to travel along that direction to reach our projected point",
            "sourceAnchor": {
              "startChar": 101,
              "endChar": 373,
              "startMarker": "This scalar is the heart of vector projection",
              "endMarker": "to reach our projected point"
            },
            "sectionIndex": 6,
            "isLeaf": true,
            "canExpand": true,
            "expanded": false
          },
          {
            "id": "section-6-chunk-1",
            "title": "Walking Along a Path Example Calculation",
            "summary": "A concrete example showing how to calculate the projection scalar using vectors a and b, resulting in traveling 0.6 times the length of b.",
            "sourceText": "Say vector b = (3, 4) has length 5. After computing the dot product a·b = 15, we divide by |b|² = 25 to get scalar 0.6. \nscalar = (a·b) / |b|² = 15/25 = 0.6 This means: travel 0.6 times the full length of b to reach the projection. Since b has length 5, we travel 0.6 × 5 = 3 units along b's direction",
            "sourceAnchor": {
              "startChar": 418,
              "endChar": 719,
              "startMarker": "Say vector b = (3, 4) has length 5",
              "endMarker": "we travel 0.6 × 5 = 3 units along b's direction"
            },
            "sectionIndex": 6,
            "isLeaf": true,
            "canExpand": true,
            "expanded": false
          },
          {
            "id": "section-6-chunk-2",
            "title": "GPS Highway Analogy for Understanding Scalars",
            "summary": "The scalar acts like GPS coordinates on a highway, telling you exactly how far along the highway to go as a fraction of reference distance.",
            "sourceText": "Think of it like GPS coordinates on a highway. Vector b is the highway, and this scalar is like saying 'your destination is at mile marker 0.6' - it tells you exactly how far along the highway to go, as a fraction of some reference distance",
            "sourceAnchor": {
              "startChar": 722,
              "endChar": 962,
              "startMarker": "Think of it like GPS coordinates on a highway",
              "endMarker": "as a fraction of some reference distance"
            },
            "sectionIndex": 6,
            "isLeaf": true,
            "canExpand": true,
            "expanded": false
          },
          {
            "id": "section-6-chunk-3",
            "title": "Complete Projection Vector Construction",
            "summary": "To get the actual projection vector, multiply the scalar by the unit vector of b, combining 'how much' with 'which way' information.",
            "sourceText": "To find the actual projection vector, multiply this scalar by the unit vector of b. The scalar tells you 'how much', and b's direction tells you 'which way' - together they give you the complete projection",
            "sourceAnchor": {
              "startChar": 975,
              "endChar": 1180,
              "startMarker": "To find the actual projection vector, multiply this scalar",
              "endMarker": "together they give you the complete projection"
            },
            "sectionIndex": 6,
            "isLeaf": true,
            "canExpand": true,
            "expanded": false
          }
        ]
      },
      {
        "id": "section-7",
        "title": "Section 8",
        "summary": "This section explains how vector projection can be extended from projecting onto a line (1D) to projecting onto a plane (2D), where you project a 3D vector onto a plane defined by two basis vectors by finding how much the vector aligns with each plane direction and combining those components.",
        "contentHash": "0653ab6038dd",
        "children": [
          {
            "id": "section-7-chunk-0",
            "title": "Projecting 3D Vectors Onto Planes Concept",
            "summary": "Introduction to projecting 3D vectors onto planes as a natural extension from projecting onto lines.",
            "sourceText": "Yes, this would make an excellent extension! Projecting a 3D vector onto a plane is the natural next step from what you've learned about projecting onto lines. \nHere's how it connects: Instead of projecting onto a single vector (which gives you a point on a line), you're projecting onto a plane defined by two vectors.",
            "sourceAnchor": {
              "startChar": 59,
              "endChar": 378,
              "startMarker": "Yes, this would make an excellent extension! Projecting a 3D vector onto a plane",
              "endMarker": "you're projecting onto a plane defined by two vectors."
            },
            "sectionIndex": 7,
            "isLeaf": true,
            "canExpand": true,
            "expanded": false
          },
          {
            "id": "section-7-chunk-1",
            "title": "Shadow Analogy for Plane Projection",
            "summary": "Visual analogy comparing plane projection to dropping a shadow onto tilted paper in 3D space.",
            "sourceText": "Think of it like dropping a shadow onto a tilted piece of paper in 3D space. The plane is spanned by your two basis vectors, and your projection will be some combination of those two vectors that gets you as close as possible to your original vector while staying in the plane.",
            "sourceAnchor": {
              "startChar": 379,
              "endChar": 656,
              "startMarker": "Think of it like dropping a shadow onto a tilted piece of paper in 3D space.",
              "endMarker": "as close as possible to your original vector while staying in the plane."
            },
            "sectionIndex": 7,
            "isLeaf": true,
            "canExpand": true,
            "expanded": false
          },
          {
            "id": "section-7-chunk-2",
            "title": "Mathematical Process for Plane Projection",
            "summary": "Explanation of how to calculate projections using dot products with two basis vectors instead of one.",
            "sourceText": "The process mirrors what you've seen: you'd find how much of your vector aligns with each of the two plane vectors (using dot products), then combine those components. It's like the 2D case but extended - instead of one component along one direction, you get two components along two directions that define your plane.",
            "sourceAnchor": {
              "startChar": 658,
              "endChar": 976,
              "startMarker": "The process mirrors what you've seen: you'd find how much of your vector aligns",
              "endMarker": "you get two components along two directions that define your plane."
            },
            "sectionIndex": 7,
            "isLeaf": true,
            "canExpand": true,
            "expanded": false
          },
          {
            "id": "section-7-chunk-3",
            "title": "Scaling from 1D to 2D Projections",
            "summary": "How projection concepts scale from projecting onto lines to projecting onto planes with visualization benefits.",
            "sourceText": "This extension would beautifully demonstrate how projection scales from 1D (onto a line) to 2D (onto a plane), and you could visualize how changing the plane's orientation affects where the shadow falls. The same geometric intuition about \"closest point\" and \"perpendicular distance\" applies, just in higher dimensions.",
            "sourceAnchor": {
              "startChar": 978,
              "endChar": 1297,
              "startMarker": "This extension would beautifully demonstrate how projection scales from 1D (onto a line) to 2D",
              "endMarker": "The same geometric intuition about \"closest point\" and \"perpendicular distance\" applies, just in higher dimensions."
            },
            "sectionIndex": 7,
            "isLeaf": true,
            "canExpand": true,
            "expanded": false
          }
        ]
      }
    ],
    "contentHash": "b8a49a7baba7",
    "generatedAt": "2026-02-08T19:55:58.877Z"
  },
  "generatedAt": "2026-02-08T19:55:58.877Z",
  "tutorialId": "vector-projection"
}